rag_doc_search/__init__.py
rag_doc_search/src/__init__.py
rag_doc_search/src/bot_models/__init__.py
rag_doc_search/src/bot_models/azure_chatbot_model.py
rag_doc_search/src/bot_models/bedrock_chatbot_model.py
rag_doc_search/src/bot_models/chatbot_model.py
rag_doc_search/src/bot_models/openai_chatbot_model.py
rag_doc_search/src/enums/__init__.py
rag_doc_search/src/enums/provider.py
rag_doc_search/src/enums/search_type.py
rag_doc_search/src/models/__init__.py
rag_doc_search/src/models/chat_response.py
rag_doc_search/src/models/user_prompt.py
rag_doc_search/src/prompt_templates/default_prompt_templates.py
rag_doc_search/utils/__init__.py
rag_doc_search/utils/callback.py
rag_doc_search/utils/config.py
rag_doc_search/utils/miscellaneous.py
rag_doc_search-0.1.9.dist-info/METADATA
rag_doc_search-0.1.9.dist-info/WHEEL
rag_doc_search-0.1.9.dist-info/RECORD
