Metadata-Version: 2.1
Name: rag-doc-search
Version: 0.1.9
Summary: This package offers a lightweight and straightforward solution for implementing Retrieval-augmented generation (RAG) functionality with large language models (LLMs).
Author: Harshad Kadam
Author-email: harshad.kadam@sourcefuse.com
Requires-Python: >=3.10,<4.0
Classifier: Programming Language :: Python :: 3
Classifier: Programming Language :: Python :: 3.10
Classifier: Programming Language :: Python :: 3.11
Requires-Dist: boto3 (>=1.34.55,<2.0.0)
Requires-Dist: botocore (>=1.34.55,<2.0.0)
Requires-Dist: django (==4.2.14)
Requires-Dist: faiss-cpu (>=1.8.0,<2.0.0)
Requires-Dist: jinja2 (>=3.1.4,<4.0.0)
Requires-Dist: langchain (>=0.2.9,<0.3.0)
Requires-Dist: langchain-aws (>=0.1.11,<0.2.0)
Requires-Dist: langchain-community (>=0.2.7,<0.3.0)
Requires-Dist: langchain-openai (>=0.1.17,<0.2.0)
Requires-Dist: openai (>=1.35.15,<2.0.0)
Requires-Dist: opensearch-py (>=2.4.2,<3.0.0)
Requires-Dist: pgvector (>=0.2.5,<0.3.0)
Requires-Dist: psycopg2-binary (>=2.9.9,<3.0.0)
Requires-Dist: setuptools (>=71.0.3,<72.0.0)
Requires-Dist: tiktoken (>=0.7.0,<0.8.0)
